veco_ai/__init__.py
veco_ai/veco_ai.py
veco_ai/veco_diarization.py
veco_ai/veco_pic_describe.py
veco_ai-0.1.0.dist-info/licenses/LICENSE
veco_ai-0.1.0.dist-info/METADATA
veco_ai-0.1.0.dist-info/WHEEL
veco_ai-0.1.0.dist-info/top_level.txt
veco_ai-0.1.0.dist-info/RECORD
