Metadata-Version: 2.4
Name: veco_ai
Version: 0.1.0
Summary: Vectorization & RAG Toolkit
Author: Matthias Pohl, Yorck Zisgen
License-Expression: CC0-1.0
Project-URL: Homepage, https://github.com/MatthiasPohlAmberg/VeCo
Project-URL: Source, https://github.com/MatthiasPohlAmberg/VeCo
Project-URL: Issues, https://github.com/MatthiasPohlAmberg/VeCo/issues
Keywords: rag,vector database,embeddings,multimodal,process mining
Classifier: Development Status :: 3 - Alpha
Classifier: Intended Audience :: Developers
Classifier: Intended Audience :: Science/Research
Classifier: Operating System :: OS Independent
Classifier: Programming Language :: Python :: 3
Classifier: Programming Language :: Python :: 3.10
Classifier: Programming Language :: Python :: 3.11
Classifier: Topic :: Scientific/Engineering :: Artificial Intelligence
Classifier: Topic :: Multimedia :: Sound/Audio :: Speech
Requires-Python: <3.12,>=3.10
License-File: LICENSE
Requires-Dist: numpy<2.0,>=1.24
Requires-Dist: scipy<1.12,>=1.10
Requires-Dist: torch<2.3,>=2.1
Requires-Dist: torchaudio<2.3,>=2.1
Requires-Dist: torchvision<0.18,>=0.16
Requires-Dist: sentence-transformers<3.0,>=2.2
Requires-Dist: faiss-cpu<1.8,>=1.7.4
Requires-Dist: moviepy<2.0,>=1.0.3
Requires-Dist: openai-whisper<20250000,>=20231117
Requires-Dist: ollama<0.3,>=0.1.6
Requires-Dist: librosa<0.11,>=0.10
Requires-Dist: soundfile<0.13,>=0.12
Requires-Dist: webrtcvad-wheels<2.1,>=2.0.10
Requires-Dist: pytesseract<0.4,>=0.3.10
Requires-Dist: Pillow<11,>=10.2
Requires-Dist: pdfplumber<0.12,>=0.11.0
Requires-Dist: python-docx<0.9,>=0.8.11
Requires-Dist: python-pptx<0.7,>=0.6.23
Requires-Dist: speechbrain<0.6,>=0.5.15
Requires-Dist: tqdm<4.67,>=4.66
Provides-Extra: dev
Requires-Dist: pytest; extra == "dev"
Requires-Dist: black; extra == "dev"
Requires-Dist: ruff; extra == "dev"
Requires-Dist: mypy; extra == "dev"
Provides-Extra: pic-describe
Requires-Dist: transformers<5,>=4.37; extra == "pic-describe"
Requires-Dist: sentencepiece<0.2,>=0.1.99; extra == "pic-describe"
Requires-Dist: sacremoses<0.1,>=0.0.53; extra == "pic-describe"
Dynamic: license-file
